pizzabot/coordinates.py
pizzabot/engine.py
pizzabot/grid.py
pizzabot/input.py
pizzabot/instructions.py
pizzabot-1.1.3.data/scripts/pizzabot
pizzabot-1.1.3.dist-info/LICENSE
pizzabot-1.1.3.dist-info/METADATA
pizzabot-1.1.3.dist-info/WHEEL
pizzabot-1.1.3.dist-info/top_level.txt
pizzabot-1.1.3.dist-info/RECORD
