Metadata-Version: 2.1
Name: pizzabot
Version: 1.1.3
Summary: UNKNOWN
Home-page: UNKNOWN
Author: light at zero
Author-email: lightatzero@gmail.com
License: UNKNOWN
Platform: UNKNOWN
Requires-Dist: pytest
